nonebot_plugin_github_release_notifier/__init__.py
nonebot_plugin_github_release_notifier/commands.py
nonebot_plugin_github_release_notifier/config.py
nonebot_plugin_github_release_notifier/data.py
nonebot_plugin_github_release_notifier/db_action.py
nonebot_plugin_github_release_notifier/debugs.py
nonebot_plugin_github_release_notifier/lang/en_us.json
nonebot_plugin_github_release_notifier/lang/zh_cn.json
nonebot_plugin_github_release_notifier/pic_process.py
nonebot_plugin_github_release_notifier/renderer/__init__.py
nonebot_plugin_github_release_notifier/renderer/context.py
nonebot_plugin_github_release_notifier/renderer/filters.py
nonebot_plugin_github_release_notifier/renderer/globals.py
nonebot_plugin_github_release_notifier/renderer/render.py
nonebot_plugin_github_release_notifier/renderer/templates/components/diff/content.html.jinja
nonebot_plugin_github_release_notifier/renderer/templates/components/diff/file.html.jinja
nonebot_plugin_github_release_notifier/renderer/templates/components/diff/header.html.jinja
nonebot_plugin_github_release_notifier/renderer/templates/components/diff/hunk-header.html.jinja
nonebot_plugin_github_release_notifier/renderer/templates/components/diff/hunk-line.html.jinja
nonebot_plugin_github_release_notifier/renderer/templates/components/diff/hunk.html.jinja
nonebot_plugin_github_release_notifier/renderer/templates/components/diff/stat.html.jinja
nonebot_plugin_github_release_notifier/renderer/templates/components/header.html.jinja
nonebot_plugin_github_release_notifier/renderer/templates/components/issue/action.html.jinja
nonebot_plugin_github_release_notifier/renderer/templates/components/issue/header.html.jinja
nonebot_plugin_github_release_notifier/renderer/templates/components/issue/label.html.jinja
nonebot_plugin_github_release_notifier/renderer/templates/components/issue/state.html.jinja
nonebot_plugin_github_release_notifier/renderer/templates/components/issue/timeline.html.jinja
nonebot_plugin_github_release_notifier-0.1.11.dist-info/METADATA
nonebot_plugin_github_release_notifier-0.1.11.dist-info/WHEEL
nonebot_plugin_github_release_notifier-0.1.11.dist-info/licenses/LICENSE
nonebot_plugin_github_release_notifier-0.1.11.dist-info/RECORD
