Metadata-Version: 2.4
Name: nonebot_plugin_github_release_notifier
Version: 0.1.11
Summary: A plugin for nonebot & onebot to notify group members of new commits, issues, and PRs in GitHub repos.
License-Expression: MIT
License-File: LICENSE
Keywords: nonebot,github,qqbot
Author: HTony03
Author-email: HTony03@foxmail.com
Requires-Python: >=3.10, <4.0
Classifier: Development Status :: 3 - Alpha
Classifier: Environment :: Plugins
Classifier: Operating System :: OS Independent
Classifier: Programming Language :: Python :: 3.10
Classifier: Programming Language :: Python :: 3.11
Classifier: Programming Language :: Python :: 3.12
Classifier: Programming Language :: Python :: 3.13
Classifier: Topic :: Software Development :: Libraries :: Python Modules
Requires-Dist: aiohttp (>=3.13.3,<4.0.0)
Requires-Dist: githubkit (>=0.13,<1.0)
Requires-Dist: humanize (>=4.12,<5.0)
Requires-Dist: jinja2 (>=3.1,<4.0)
Requires-Dist: linkify-it-py (>=2.0,<3.0)
Requires-Dist: markdown-it-py (>=3,<5)
Requires-Dist: mdit-py-emoji (>=0.1,<1.0)
Requires-Dist: mdit-py-plugins (>=0.4,<1.0)
Requires-Dist: nonebot-adapter-onebot (>=2.4,<3.0)
Requires-Dist: nonebot-plugin-apscheduler (>=0.3,<1.0)
Requires-Dist: nonebot-plugin-htmlrender (>=0.7.0a2,<0.8.0)
Requires-Dist: nonebot-plugin-localstore (>=0.7,<1.0)
Requires-Dist: nonebot2 (>=2.3,<3.0)
Requires-Dist: packaging (>=25.0,<26.0)
Requires-Dist: pathlib (>=1.0,<2.0)
Requires-Dist: tenacity (>=9.1,<10.0)
Requires-Dist: typing-extensions (>=4.14,<5.0)
Project-URL: Homepage, https://github.com/HTony03/nonebot_plugin_github_release_notifier
Project-URL: Repository, https://github.com/HTony03/nonebot_plugin_github_release_notifier
Project-URL: changelog, https://github.com/HTony03/nonebot_plugin_github_release_notifier/releases
Project-URL: issue, https://github.com/HTony03/nonebot_plugin_github_release_notifier/issues
